smart_ocr/__init__.py
smart_ocr/cli.py
smart_ocr/audit/__init__.py
smart_ocr/audit/heuristics.py
smart_ocr/audit/llm_audit.py
smart_ocr/core/__init__.py
smart_ocr/core/config.py
smart_ocr/core/document.py
smart_ocr/core/result.py
smart_ocr/engines/__init__.py
smart_ocr/engines/base.py
smart_ocr/engines/deepseek.py
smart_ocr/engines/deepseek_vllm.py
smart_ocr/engines/gemini.py
smart_ocr/engines/mistral.py
smart_ocr/engines/nougat.py
smart_ocr/engines/vllm.py
smart_ocr/engines/vllm_manager.py
smart_ocr/pipeline/__init__.py
smart_ocr/pipeline/hpc_pipeline.py
smart_ocr/pipeline/hpc_sequential_pipeline.py
smart_ocr/pipeline/processor.py
smart_ocr/pipeline/reconciler.py
smart_ocr/pipeline/router.py
smart_ocr/ui/__init__.py
smart_ocr/ui/console.py
smart_ocr/ui/panels.py
smart_ocr/ui/progress.py
smart_ocr/ui/theme.py
smart_ocr-0.2.7.dist-info/METADATA
smart_ocr-0.2.7.dist-info/WHEEL
smart_ocr-0.2.7.dist-info/entry_points.txt
smart_ocr-0.2.7.dist-info/licenses/LICENSE
smart_ocr-0.2.7.dist-info/RECORD
