Metadata-Version: 2.4
Name: smart-ocr
Version: 0.2.7
Summary: Multi-engine document OCR with cascading fallback
Project-URL: Homepage, https://github.com/r-uben/smart-ocr
Project-URL: Repository, https://github.com/r-uben/smart-ocr
Project-URL: Issues, https://github.com/r-uben/smart-ocr/issues
Author-email: Ruben Fernandez-Fuertes <fernandezfuertesruben@gmail.com>
License: MIT
License-File: LICENSE
Keywords: deepseek,document-processing,gemini,mistral,nougat,ocr,pdf,smart-ocr
Classifier: Development Status :: 4 - Beta
Classifier: Intended Audience :: Developers
Classifier: Intended Audience :: Science/Research
Classifier: License :: OSI Approved :: MIT License
Classifier: Operating System :: OS Independent
Classifier: Programming Language :: Python :: 3
Classifier: Programming Language :: Python :: 3.11
Classifier: Programming Language :: Python :: 3.12
Requires-Python: <3.13,>=3.11
Requires-Dist: click>=8.1.0
Requires-Dist: httpx>=0.27.0
Requires-Dist: pillow>=10.0.0
Requires-Dist: pymupdf>=1.24.0
Requires-Dist: pyyaml>=6.0.0
Requires-Dist: rich>=13.0.0
Provides-Extra: all
Requires-Dist: deepseek-ocr-cli>=0.1.0; extra == 'all'
Requires-Dist: gemini-ocr-cli>=0.2.0; extra == 'all'
Requires-Dist: mistral-ocr-cli>=0.1.0; extra == 'all'
Requires-Dist: nougat-ocr-cli>=0.1.2; extra == 'all'
Provides-Extra: cloud
Requires-Dist: gemini-ocr-cli>=0.2.0; extra == 'cloud'
Requires-Dist: mistral-ocr-cli>=0.1.0; extra == 'cloud'
Provides-Extra: deepseek
Requires-Dist: deepseek-ocr-cli>=0.1.0; extra == 'deepseek'
Provides-Extra: dev
Requires-Dist: pytest-cov>=4.0.0; extra == 'dev'
Requires-Dist: pytest>=8.0.0; extra == 'dev'
Requires-Dist: ruff>=0.8.0; extra == 'dev'
Provides-Extra: gemini
Requires-Dist: gemini-ocr-cli>=0.2.0; extra == 'gemini'
Provides-Extra: local
Requires-Dist: deepseek-ocr-cli>=0.1.0; extra == 'local'
Requires-Dist: nougat-ocr-cli>=0.1.2; extra == 'local'
Provides-Extra: mistral
Requires-Dist: mistral-ocr-cli>=0.1.0; extra == 'mistral'
Provides-Extra: nougat
Requires-Dist: nougat-ocr-cli>=0.1.2; extra == 'nougat'
